mini_python/.DS_Store
mini_python/__init__.py
mini_python/app.py
mini_python/static/css/style.css
mini_python/templates/base.html
mini_python/templates/create.html
mini_python/templates/edit.html
mini_python/templates/index.html
mini_python/templates/post.html
mini_python-0.1.5.dist-info/LICENSE
mini_python-0.1.5.dist-info/METADATA
mini_python-0.1.5.dist-info/WHEEL
mini_python-0.1.5.dist-info/RECORD
