Metadata-Version: 2.1
Name: mini-python
Version: 0.1.5
Summary: 
Author: Naveen Thurimerla
Author-email: nawinto99@gmail.com
Requires-Python: >=3.9,<4.0
Classifier: Programming Language :: Python :: 3
Classifier: Programming Language :: Python :: 3.9
Classifier: Programming Language :: Python :: 3.10
Classifier: Programming Language :: Python :: 3.11
Requires-Dist: flask (>=2.2.3,<3.0.0)
Requires-Dist: python-dotenv (>=1.0.0,<2.0.0)
